nextpress/__init__.py
nextpress/errors.py
nextpress/middlewares.py
nextpress/nextpress.py
nextpress/types/__init__.py
nextpress/types/request.py
nextpress/types/response.py
nextpress/utils/__init__.py
nextpress/utils/asgi.py
nextpress/utils/server.py
nextpress/utils/types.py
nextpress-0.1.0.dist-info/METADATA
nextpress-0.1.0.dist-info/WHEEL
nextpress-0.1.0.dist-info/RECORD
