Metadata-Version: 2.4
Name: nextpress
Version: 0.1.0
Summary: nth python framework
Requires-Python: >=3.13
Requires-Dist: pydantic>=2.11.9
